opensearch_xml/__about__.py
opensearch_xml/__init__.py
opensearch_xml/apps.py
opensearch_xml/conf.py
opensearch_xml/urls.py
opensearch_xml/views.py
opensearch_xml/templates/opensearch_xml/opensearch.xml
opensearch_xml/templates/opensearch_xml/tags/opensearch_xml_meta.html
opensearch_xml/templatetags/__init__.py
opensearch_xml/templatetags/opensearch_xml_tags.py
django_opensearch_xml-0.3.2.dist-info/METADATA
django_opensearch_xml-0.3.2.dist-info/WHEEL
django_opensearch_xml-0.3.2.dist-info/licenses/LICENSE
django_opensearch_xml-0.3.2.dist-info/RECORD
