Metadata-Version: 2.4
Name: django-opensearch-xml
Version: 0.3.2
Summary: Handle opensearch.xml
Project-URL: Homepage, https://gitlab.com/frague59/django-opensearch-xml
Author-email: François GUÉRIN <frague59@gmail.com>
License-Expression: MIT
License-File: LICENSE
Keywords: django,opensearch,opensearch.xml
Classifier: Development Status :: 3 - Alpha
Classifier: Environment :: Plugins
Classifier: Environment :: Web Environment
Classifier: Framework :: Django :: 3.2
Classifier: Framework :: Django :: 4.0
Classifier: Framework :: Django :: 4.1
Classifier: Framework :: Django :: 4.2
Classifier: Framework :: Django :: 5.0
Classifier: Framework :: Django :: 5.1
Classifier: Framework :: Django :: 5.2
Classifier: Intended Audience :: Developers
Classifier: Intended Audience :: Information Technology
Classifier: License :: OSI Approved :: MIT License
Classifier: Operating System :: Unix
Classifier: Programming Language :: Python :: 3.7
Classifier: Programming Language :: Python :: 3.8
Classifier: Programming Language :: Python :: 3.9
Classifier: Programming Language :: Python :: 3.10
Classifier: Programming Language :: Python :: 3.11
Classifier: Programming Language :: Python :: 3.12
Classifier: Programming Language :: Python :: 3.13
Classifier: Topic :: Utilities
Requires-Python: >=3.9
Requires-Dist: django-appconf>=1.0.6
Requires-Dist: django<6.0,>=3.2
